nozomi/__init__.py
nozomi/api.py
nozomi/data.py
nozomi/exceptions.py
nozomi/helpers.py
python_nozomi-2.0.0.dist-info/LICENSE
python_nozomi-2.0.0.dist-info/METADATA
python_nozomi-2.0.0.dist-info/WHEEL
python_nozomi-2.0.0.dist-info/top_level.txt
python_nozomi-2.0.0.dist-info/RECORD
