Metadata-Version: 2.1
Name: python-nozomi
Version: 2.0.0
Summary: Nozomi API for retrieving images, videos, gifs.
Home-page: https://github.com/Alfa-Q/python-nozomi
Download-URL: https://github.com/Alfa-Q/python-nozomi/archive/2.0.0.tar.gz
Author: Alfa_Q
Author-email: alfakyuu@gmail.com
License: MIT
Keywords: nozomi,nozomi.la,api,video,image,anime
Classifier: Development Status :: 3 - Alpha
Classifier: Intended Audience :: Developers
Classifier: Topic :: Software Development :: Build Tools
Classifier: License :: OSI Approved :: MIT License
Classifier: Programming Language :: Python :: 3.7
Classifier: Programming Language :: Python :: 3.8
Classifier: Programming Language :: Python :: 3.9
Classifier: Programming Language :: Python :: 3.10
Classifier: Programming Language :: Python :: 3.11
Requires-Python: >=3.7
License-File: LICENSE
Requires-Dist: requests
Requires-Dist: dacite
Provides-Extra: dev
Requires-Dist: pytest ; extra == 'dev'
